setup.py
eduextractor/__init__.py
eduextractor/base.py
eduextractor/browser.py
eduextractor/cli.py
eduextractor/config.py
eduextractor/map_loader.py
eduextractor/table.py
eduextractor.egg-info/PKG-INFO
eduextractor.egg-info/SOURCES.txt
eduextractor.egg-info/dependency_links.txt
eduextractor.egg-info/entry_points.txt
eduextractor.egg-info/pbr.json
eduextractor.egg-info/requires.txt
eduextractor.egg-info/top_level.txt
eduextractor/sis/__init__.py
eduextractor/sis/illuminate/__init__.py
eduextractor/sis/illuminate/illuminate_exporter.py
eduextractor/sis/powerschool/__init__.py
eduextractor/sis/powerschool/powerschool_exporter.py