Metadata-Version: 1.1
Name: eduextractor
Version: 0.0.2
Summary: Open Extraction Tools for Education
Home-page: https://github.com/openEduConnect/eduextractor
Author: Hunter Owens
Author-email: Hunter@hunterowens.net
License: MIT
Keywords: sample setuptools development
Platform: UNKNOWN
Classifier: Development Status :: 3 - Alpha
Classifier: Intended Audience :: Developers
Classifier: License :: OSI Approved :: MIT License
Classifier: Programming Language :: Python :: 2
Classifier: Programming Language :: Python :: 2.6
Classifier: Programming Language :: Python :: 2.7
Classifier: Programming Language :: Python :: 3.2
Classifier: Programming Language :: Python :: 3.3
Classifier: Programming Language :: Python :: 3.4
